[
  {
    "line": 1,
    "elements": [
      {
        "before": [
          {
            "result": {
              "duration": 8819533000,
              "status": "passed"
            },
            "match": {
              "location": "Hooks.open()"
            }
          }
        ],
        "line": 3,
        "name": "offset reports",
        "description": "",
        "id": "school-offset-report;offset-reports",
        "type": "scenario",
        "keyword": "Scenario",
        "steps": [
          {
            "result": {
              "duration": 102577500,
              "status": "passed"
            },
            "line": 4,
            "name": "User is on school homepage",
            "match": {
              "location": "StepDef.user_is_on_school_homepage()"
            },
            "keyword": "Given "
          },
          {
            "result": {
              "duration": 1232429800,
              "status": "passed"
            },
            "line": 5,
            "name": "User navigate to Results and find offset reports",
            "match": {
              "location": "StepDefOffset.user_navigate_to_Results_and_find_offset_reports()"
            },
            "keyword": "When "
          },
          {
            "result": {
              "duration": 156597700,
              "status": "passed"
            },
            "line": 6,
            "name": "User can access any offset report",
            "match": {
              "location": "StepDefOffset.user_can_access_any_offset_report()"
            },
            "keyword": "Then "
          }
        ]
      }
    ],
    "name": "School offset report",
    "description": "",
    "id": "school-offset-report",
    "keyword": "Feature",
    "uri": "C:/Users/bhupe/WembleyHigh/src/test/Resources/offset.feature"
  }
]